{
  "source": "traffic_aware_demand_monitoring_priority_v2",
  "generated_at": "2026-05-15T21:30:54.158Z",
  "forecast_source": "model",
  "forecast_target_datetime": "2026-05-16T07:00:00+09:00",
  "forecast_strategy": "pattern",
  "traffic_source": "citydata_road_traffic_dong_filtered",
  "traffic_collected_at": "2026-05-15T21:30:30.905Z",
  "policy": "imbalance_score = predicted_demand_score - road_accessibility_proxy; priority_units are monitoring priority bands, not taxi counts",
  "policy_effect_summary": {
    "method": "proxy_counterfactual_v1",
    "interpretation": "Estimated pressure relief from monitoring units and incentive multipliers. This is a policy-planning proxy, not measured dispatch impact.",
    "intervention_area_count": 2,
    "total_monitoring_units": 5,
    "max_incentive_multiplier": 1.2,
    "total_positive_imbalance_before": 0.763,
    "estimated_total_positive_imbalance_after": 0.258,
    "estimated_total_relief_score": 0.505,
    "highest_relief_dong": "삼성1동"
  },
  "decisions": [
    {
      "dong_name": "삼성1동",
      "predicted_demand_score": 1,
      "confidence": 0.58,
      "supply_proxy_score": 0.52,
      "supply_source": "citydata_congestion_and_speed",
      "congestion_score": 0.537,
      "avg_speed_kmh": 22.8,
      "link_count": 12,
      "congested_link_count": 2,
      "slow_link_count": 5,
      "imbalance_score": 0.48,
      "action": "수요 집중 매우 높음",
      "action_level": "high",
      "coverage_units": 3,
      "incentive_multiplier": 1.2,
      "policy_effect_estimate": {
        "method": "proxy_counterfactual_v1",
        "before_positive_imbalance_score": 0.48,
        "estimated_relief_score": 0.31,
        "after_policy_imbalance_score": 0.17,
        "note": "Proxy relief estimate only; not observed taxi-call or taxi-supply impact."
      }
    },
    {
      "dong_name": "대치4동",
      "predicted_demand_score": 0.673,
      "confidence": 0.58,
      "supply_proxy_score": 0.405,
      "supply_source": "citydata_congestion_and_speed",
      "congestion_score": 0.653,
      "avg_speed_kmh": 18.9,
      "link_count": 18,
      "congested_link_count": 7,
      "slow_link_count": 7,
      "imbalance_score": 0.268,
      "action": "수요 집중 높음",
      "action_level": "medium",
      "coverage_units": 2,
      "incentive_multiplier": 1.1,
      "policy_effect_estimate": {
        "method": "proxy_counterfactual_v1",
        "before_positive_imbalance_score": 0.268,
        "estimated_relief_score": 0.195,
        "after_policy_imbalance_score": 0.073,
        "note": "Proxy relief estimate only; not observed taxi-call or taxi-supply impact."
      }
    },
    {
      "dong_name": "논현1동",
      "predicted_demand_score": 0.627,
      "confidence": 0.58,
      "supply_proxy_score": 0.612,
      "supply_source": "citydata_congestion_and_speed",
      "congestion_score": 0.414,
      "avg_speed_kmh": 23.6,
      "link_count": 19,
      "congested_link_count": 2,
      "slow_link_count": 8,
      "imbalance_score": 0.015,
      "action": "안정",
      "action_level": "low",
      "coverage_units": 0,
      "incentive_multiplier": 1,
      "policy_effect_estimate": {
        "method": "proxy_counterfactual_v1",
        "before_positive_imbalance_score": 0.015,
        "estimated_relief_score": 0,
        "after_policy_imbalance_score": 0.015,
        "note": "Proxy relief estimate only; not observed taxi-call or taxi-supply impact."
      }
    },
    {
      "dong_name": "역삼1동",
      "predicted_demand_score": 0.486,
      "confidence": 0.58,
      "supply_proxy_score": 0.534,
      "supply_source": "citydata_congestion_and_speed",
      "congestion_score": 0.523,
      "avg_speed_kmh": 23.3,
      "link_count": 91,
      "congested_link_count": 24,
      "slow_link_count": 38,
      "imbalance_score": -0.048,
      "action": "안정",
      "action_level": "low",
      "coverage_units": 0,
      "incentive_multiplier": 1,
      "policy_effect_estimate": {
        "method": "proxy_counterfactual_v1",
        "before_positive_imbalance_score": 0,
        "estimated_relief_score": 0,
        "after_policy_imbalance_score": 0,
        "note": "Proxy relief estimate only; not observed taxi-call or taxi-supply impact."
      }
    },
    {
      "dong_name": "논현2동",
      "predicted_demand_score": 0.564,
      "confidence": 0.58,
      "supply_proxy_score": 0.703,
      "supply_source": "citydata_congestion_and_speed",
      "congestion_score": 0.334,
      "avg_speed_kmh": 27.6,
      "link_count": 2,
      "congested_link_count": 0,
      "slow_link_count": 1,
      "imbalance_score": -0.139,
      "action": "안정",
      "action_level": "low",
      "coverage_units": 0,
      "incentive_multiplier": 1,
      "policy_effect_estimate": {
        "method": "proxy_counterfactual_v1",
        "before_positive_imbalance_score": 0,
        "estimated_relief_score": 0,
        "after_policy_imbalance_score": 0,
        "note": "Proxy relief estimate only; not observed taxi-call or taxi-supply impact."
      }
    },
    {
      "dong_name": "청담동",
      "predicted_demand_score": 0.148,
      "confidence": 0.58,
      "supply_proxy_score": 0.572,
      "supply_source": "citydata_congestion_and_speed",
      "congestion_score": 0.477,
      "avg_speed_kmh": 24,
      "link_count": 33,
      "congested_link_count": 5,
      "slow_link_count": 15,
      "imbalance_score": -0.424,
      "action": "안정",
      "action_level": "low",
      "coverage_units": 0,
      "incentive_multiplier": 1,
      "policy_effect_estimate": {
        "method": "proxy_counterfactual_v1",
        "before_positive_imbalance_score": 0,
        "estimated_relief_score": 0,
        "after_policy_imbalance_score": 0,
        "note": "Proxy relief estimate only; not observed taxi-call or taxi-supply impact."
      }
    },
    {
      "dong_name": "삼성2동",
      "predicted_demand_score": 0.163,
      "confidence": 0.58,
      "supply_proxy_score": 0.644,
      "supply_source": "citydata_congestion_and_speed",
      "congestion_score": 0.397,
      "avg_speed_kmh": 25.9,
      "link_count": 23,
      "congested_link_count": 1,
      "slow_link_count": 13,
      "imbalance_score": -0.481,
      "action": "안정",
      "action_level": "low",
      "coverage_units": 0,
      "incentive_multiplier": 1,
      "policy_effect_estimate": {
        "method": "proxy_counterfactual_v1",
        "before_positive_imbalance_score": 0,
        "estimated_relief_score": 0,
        "after_policy_imbalance_score": 0,
        "note": "Proxy relief estimate only; not observed taxi-call or taxi-supply impact."
      }
    },
    {
      "dong_name": "역삼2동",
      "predicted_demand_score": 0,
      "confidence": 0.58,
      "supply_proxy_score": 0.531,
      "supply_source": "citydata_congestion_and_speed",
      "congestion_score": 0.499,
      "avg_speed_kmh": 21,
      "link_count": 19,
      "congested_link_count": 6,
      "slow_link_count": 6,
      "imbalance_score": -0.531,
      "action": "안정",
      "action_level": "low",
      "coverage_units": 0,
      "incentive_multiplier": 1,
      "policy_effect_estimate": {
        "method": "proxy_counterfactual_v1",
        "before_positive_imbalance_score": 0,
        "estimated_relief_score": 0,
        "after_policy_imbalance_score": 0,
        "note": "Proxy relief estimate only; not observed taxi-call or taxi-supply impact."
      }
    },
    {
      "dong_name": "신사동",
      "predicted_demand_score": 0.006,
      "confidence": 0.58,
      "supply_proxy_score": 0.751,
      "supply_source": "citydata_congestion_and_speed",
      "congestion_score": 0.356,
      "avg_speed_kmh": 40,
      "link_count": 47,
      "congested_link_count": 7,
      "slow_link_count": 15,
      "imbalance_score": -0.745,
      "action": "안정",
      "action_level": "low",
      "coverage_units": 0,
      "incentive_multiplier": 1,
      "policy_effect_estimate": {
        "method": "proxy_counterfactual_v1",
        "before_positive_imbalance_score": 0,
        "estimated_relief_score": 0,
        "after_policy_imbalance_score": 0,
        "note": "Proxy relief estimate only; not observed taxi-call or taxi-supply impact."
      }
    }
  ]
}
