{
  "generated_at": "2026-05-17T16:29:50.302Z",
  "source_log_path": "data/processed/live_validation/live_forecast_log.jsonl",
  "traffic_source_dir": "data/raw/traffic",
  "status": "has_completed_comparison",
  "note": "Live comparison pairs saved demand-proxy forecasts with road congestion observed by Seoul citydata after the forecast target time. Public transit/taxi-call demand labels are separate and may arrive later.",
  "match_window_minutes": 90,
  "log_count": 247,
  "completed_count": 2,
  "waiting_count": 245,
  "latest": {
    "kind": "completed",
    "generated_at": "2026-05-18T00:31:01+09:00",
    "target_datetime": "2026-05-18T01:00:00+09:00",
    "feature_datetime": "2026-05-18T00:00:00+09:00",
    "strategy": "pattern",
    "actual_observed_at": "2026-05-17T16:29:40.251Z",
    "actual_snapshot_path": "data/raw/traffic/2026-05-18/0129.json",
    "comparison_type": "forecast_demand_score_vs_observed_road_congestion",
    "note": "Forecast is a movement-demand proxy score. Observed value is Seoul citydata road congestion at/after the target time. This is a live signal check, not taxi-call accuracy.",
    "overall": {
      "row_count": 5,
      "spearman_r": -0.2,
      "mean_abs_score_gap": 0.3104,
      "top_forecast_dong": "역삼1동",
      "top_observed_congestion_dong": "대치4동",
      "same_top_dong": false
    },
    "rows": [
      {
        "dong_name": "역삼1동",
        "forecast_score": 1,
        "forecast_raw_prediction": 5.118771,
        "forecast_confidence": 0.58,
        "observed_congestion_score": 0.514,
        "observed_avg_speed_kmh": 23.4,
        "observed_link_count": 91,
        "forecast_rank": 1,
        "observed_congestion_rank": 3,
        "score_gap": 0.486,
        "abs_score_gap": 0.486,
        "rank_gap": -2
      },
      {
        "dong_name": "논현1동",
        "forecast_score": 0.3642,
        "forecast_raw_prediction": 2.326111,
        "forecast_confidence": 0.58,
        "observed_congestion_score": 0.395,
        "observed_avg_speed_kmh": 25.5,
        "observed_link_count": 19,
        "forecast_rank": 2,
        "observed_congestion_rank": 5,
        "score_gap": -0.0308,
        "abs_score_gap": 0.0308,
        "rank_gap": -3
      },
      {
        "dong_name": "삼성1동",
        "forecast_score": 0.2701,
        "forecast_raw_prediction": 1.913061,
        "forecast_confidence": 0.58,
        "observed_congestion_score": 0.553,
        "observed_avg_speed_kmh": 23.1,
        "observed_link_count": 12,
        "forecast_rank": 3,
        "observed_congestion_rank": 2,
        "score_gap": -0.2829,
        "abs_score_gap": 0.2829,
        "rank_gap": 1
      },
      {
        "dong_name": "대치4동",
        "forecast_score": 0.2592,
        "forecast_raw_prediction": 1.865251,
        "forecast_confidence": 0.58,
        "observed_congestion_score": 0.677,
        "observed_avg_speed_kmh": 16.1,
        "observed_link_count": 18,
        "forecast_rank": 4,
        "observed_congestion_rank": 1,
        "score_gap": -0.4178,
        "abs_score_gap": 0.4178,
        "rank_gap": 3
      },
      {
        "dong_name": "청담동",
        "forecast_score": 0.1575,
        "forecast_raw_prediction": 1.418607,
        "forecast_confidence": 0.58,
        "observed_congestion_score": 0.492,
        "observed_avg_speed_kmh": 25.5,
        "observed_link_count": 33,
        "forecast_rank": 5,
        "observed_congestion_rank": 4,
        "score_gap": -0.3345,
        "abs_score_gap": 0.3345,
        "rank_gap": 1
      }
    ]
  },
  "completed": [
    {
      "generated_at": "2026-05-17T23:38:59+09:00",
      "target_datetime": "2026-05-18T00:00:00+09:00",
      "feature_datetime": "2026-05-17T23:00:00+09:00",
      "strategy": "pattern",
      "actual_observed_at": "2026-05-17T16:29:40.251Z",
      "actual_snapshot_path": "data/raw/traffic/2026-05-18/0129.json",
      "comparison_type": "forecast_demand_score_vs_observed_road_congestion",
      "note": "Forecast is a movement-demand proxy score. Observed value is Seoul citydata road congestion at/after the target time. This is a live signal check, not taxi-call accuracy.",
      "overall": {
        "row_count": 5,
        "spearman_r": -0.3,
        "mean_abs_score_gap": 0.2818,
        "top_forecast_dong": "논현1동",
        "top_observed_congestion_dong": "대치4동",
        "same_top_dong": false
      },
      "rows": [
        {
          "dong_name": "논현1동",
          "forecast_score": 1,
          "forecast_raw_prediction": 6.433976,
          "forecast_confidence": 0.58,
          "observed_congestion_score": 0.395,
          "observed_avg_speed_kmh": 25.5,
          "observed_link_count": 19,
          "forecast_rank": 1,
          "observed_congestion_rank": 5,
          "score_gap": 0.605,
          "abs_score_gap": 0.605,
          "rank_gap": -4
        },
        {
          "dong_name": "역삼1동",
          "forecast_score": 0.7454,
          "forecast_raw_prediction": 4.861454,
          "forecast_confidence": 0.58,
          "observed_congestion_score": 0.514,
          "observed_avg_speed_kmh": 23.4,
          "observed_link_count": 91,
          "forecast_rank": 2,
          "observed_congestion_rank": 3,
          "score_gap": 0.2314,
          "abs_score_gap": 0.2314,
          "rank_gap": -1
        },
        {
          "dong_name": "대치4동",
          "forecast_score": 0.5173,
          "forecast_raw_prediction": 3.453206,
          "forecast_confidence": 0.58,
          "observed_congestion_score": 0.677,
          "observed_avg_speed_kmh": 16.1,
          "observed_link_count": 18,
          "forecast_rank": 3,
          "observed_congestion_rank": 1,
          "score_gap": -0.1597,
          "abs_score_gap": 0.1597,
          "rank_gap": 2
        },
        {
          "dong_name": "삼성1동",
          "forecast_score": 0.4731,
          "forecast_raw_prediction": 3.179917,
          "forecast_confidence": 0.58,
          "observed_congestion_score": 0.553,
          "observed_avg_speed_kmh": 23.1,
          "observed_link_count": 12,
          "forecast_rank": 4,
          "observed_congestion_rank": 2,
          "score_gap": -0.0799,
          "abs_score_gap": 0.0799,
          "rank_gap": 2
        },
        {
          "dong_name": "청담동",
          "forecast_score": 0.159,
          "forecast_raw_prediction": 1.24013,
          "forecast_confidence": 0.58,
          "observed_congestion_score": 0.492,
          "observed_avg_speed_kmh": 25.5,
          "observed_link_count": 33,
          "forecast_rank": 5,
          "observed_congestion_rank": 4,
          "score_gap": -0.333,
          "abs_score_gap": 0.333,
          "rank_gap": 1
        }
      ]
    },
    {
      "generated_at": "2026-05-18T00:31:01+09:00",
      "target_datetime": "2026-05-18T01:00:00+09:00",
      "feature_datetime": "2026-05-18T00:00:00+09:00",
      "strategy": "pattern",
      "actual_observed_at": "2026-05-17T16:29:40.251Z",
      "actual_snapshot_path": "data/raw/traffic/2026-05-18/0129.json",
      "comparison_type": "forecast_demand_score_vs_observed_road_congestion",
      "note": "Forecast is a movement-demand proxy score. Observed value is Seoul citydata road congestion at/after the target time. This is a live signal check, not taxi-call accuracy.",
      "overall": {
        "row_count": 5,
        "spearman_r": -0.2,
        "mean_abs_score_gap": 0.3104,
        "top_forecast_dong": "역삼1동",
        "top_observed_congestion_dong": "대치4동",
        "same_top_dong": false
      },
      "rows": [
        {
          "dong_name": "역삼1동",
          "forecast_score": 1,
          "forecast_raw_prediction": 5.118771,
          "forecast_confidence": 0.58,
          "observed_congestion_score": 0.514,
          "observed_avg_speed_kmh": 23.4,
          "observed_link_count": 91,
          "forecast_rank": 1,
          "observed_congestion_rank": 3,
          "score_gap": 0.486,
          "abs_score_gap": 0.486,
          "rank_gap": -2
        },
        {
          "dong_name": "논현1동",
          "forecast_score": 0.3642,
          "forecast_raw_prediction": 2.326111,
          "forecast_confidence": 0.58,
          "observed_congestion_score": 0.395,
          "observed_avg_speed_kmh": 25.5,
          "observed_link_count": 19,
          "forecast_rank": 2,
          "observed_congestion_rank": 5,
          "score_gap": -0.0308,
          "abs_score_gap": 0.0308,
          "rank_gap": -3
        },
        {
          "dong_name": "삼성1동",
          "forecast_score": 0.2701,
          "forecast_raw_prediction": 1.913061,
          "forecast_confidence": 0.58,
          "observed_congestion_score": 0.553,
          "observed_avg_speed_kmh": 23.1,
          "observed_link_count": 12,
          "forecast_rank": 3,
          "observed_congestion_rank": 2,
          "score_gap": -0.2829,
          "abs_score_gap": 0.2829,
          "rank_gap": 1
        },
        {
          "dong_name": "대치4동",
          "forecast_score": 0.2592,
          "forecast_raw_prediction": 1.865251,
          "forecast_confidence": 0.58,
          "observed_congestion_score": 0.677,
          "observed_avg_speed_kmh": 16.1,
          "observed_link_count": 18,
          "forecast_rank": 4,
          "observed_congestion_rank": 1,
          "score_gap": -0.4178,
          "abs_score_gap": 0.4178,
          "rank_gap": 3
        },
        {
          "dong_name": "청담동",
          "forecast_score": 0.1575,
          "forecast_raw_prediction": 1.418607,
          "forecast_confidence": 0.58,
          "observed_congestion_score": 0.492,
          "observed_avg_speed_kmh": 25.5,
          "observed_link_count": 33,
          "forecast_rank": 5,
          "observed_congestion_rank": 4,
          "score_gap": -0.3345,
          "abs_score_gap": 0.3345,
          "rank_gap": 1
        }
      ]
    }
  ],
  "waiting": [
    {
      "generated_at": "2026-05-17T00:30:38+09:00",
      "target_datetime": "2026-05-17T01:00:00+09:00",
      "feature_datetime": "2026-05-17T00:00:00+09:00",
      "strategy": "pattern",
      "top_forecast_dong": "논현1동",
      "top_forecast_score": 1,
      "status": "waiting_for_observed_snapshot"
    },
    {
      "generated_at": "2026-05-17T01:28:16+09:00",
      "target_datetime": "2026-05-17T02:00:00+09:00",
      "feature_datetime": "2026-05-17T01:00:00+09:00",
      "strategy": "pattern",
      "top_forecast_dong": "논현1동",
      "top_forecast_score": 1,
      "status": "waiting_for_observed_snapshot"
    },
    {
      "generated_at": "2026-05-17T02:29:03+09:00",
      "target_datetime": "2026-05-17T03:00:00+09:00",
      "feature_datetime": "2026-05-17T02:00:00+09:00",
      "strategy": "pattern",
      "top_forecast_dong": "논현1동",
      "top_forecast_score": 1,
      "status": "waiting_for_observed_snapshot"
    },
    {
      "generated_at": "2026-05-17T03:30:46+09:00",
      "target_datetime": "2026-05-17T04:00:00+09:00",
      "feature_datetime": "2026-05-17T03:00:00+09:00",
      "strategy": "pattern",
      "top_forecast_dong": "삼성1동",
      "top_forecast_score": 1,
      "status": "waiting_for_observed_snapshot"
    },
    {
      "generated_at": "2026-05-17T04:33:21+09:00",
      "target_datetime": "2026-05-17T05:00:00+09:00",
      "feature_datetime": "2026-05-17T04:00:00+09:00",
      "strategy": "pattern",
      "top_forecast_dong": "삼성1동",
      "top_forecast_score": 1,
      "status": "waiting_for_observed_snapshot"
    },
    {
      "generated_at": "2026-05-17T05:24:12+09:00",
      "target_datetime": "2026-05-17T06:00:00+09:00",
      "feature_datetime": "2026-05-17T05:00:00+09:00",
      "strategy": "pattern",
      "top_forecast_dong": "삼성1동",
      "top_forecast_score": 1,
      "status": "waiting_for_observed_snapshot"
    },
    {
      "generated_at": "2026-05-17T06:24:49+09:00",
      "target_datetime": "2026-05-17T07:00:00+09:00",
      "feature_datetime": "2026-05-17T06:00:00+09:00",
      "strategy": "pattern",
      "top_forecast_dong": "삼성1동",
      "top_forecast_score": 1,
      "status": "waiting_for_observed_snapshot"
    },
    {
      "generated_at": "2026-05-17T07:24:21+09:00",
      "target_datetime": "2026-05-17T08:00:00+09:00",
      "feature_datetime": "2026-05-17T07:00:00+09:00",
      "strategy": "pattern",
      "top_forecast_dong": "삼성1동",
      "top_forecast_score": 1,
      "status": "waiting_for_observed_snapshot"
    },
    {
      "generated_at": "2026-05-17T08:25:59+09:00",
      "target_datetime": "2026-05-17T09:00:00+09:00",
      "feature_datetime": "2026-05-17T08:00:00+09:00",
      "strategy": "pattern",
      "top_forecast_dong": "삼성1동",
      "top_forecast_score": 1,
      "status": "waiting_for_observed_snapshot"
    },
    {
      "generated_at": "2026-05-17T10:14:31+09:00",
      "target_datetime": "2026-05-17T11:00:00+09:00",
      "feature_datetime": "2026-05-17T10:00:00+09:00",
      "strategy": "pattern",
      "top_forecast_dong": "논현1동",
      "top_forecast_score": 1,
      "status": "waiting_for_observed_snapshot"
    },
    {
      "generated_at": "2026-05-17T12:21:06+09:00",
      "target_datetime": "2026-05-17T13:00:00+09:00",
      "feature_datetime": "2026-05-17T12:00:00+09:00",
      "strategy": "pattern",
      "top_forecast_dong": "논현1동",
      "top_forecast_score": 1,
      "status": "waiting_for_observed_snapshot"
    },
    {
      "generated_at": "2026-05-17T14:27:29+09:00",
      "target_datetime": "2026-05-17T15:00:00+09:00",
      "feature_datetime": "2026-05-17T14:00:00+09:00",
      "strategy": "pattern",
      "top_forecast_dong": "논현1동",
      "top_forecast_score": 1,
      "status": "waiting_for_observed_snapshot"
    },
    {
      "generated_at": "2026-05-17T16:12:43+09:00",
      "target_datetime": "2026-05-17T17:00:00+09:00",
      "feature_datetime": "2026-05-17T16:00:00+09:00",
      "strategy": "pattern",
      "top_forecast_dong": "논현1동",
      "top_forecast_score": 1,
      "status": "waiting_for_observed_snapshot"
    },
    {
      "generated_at": "2026-05-17T17:53:41+09:00",
      "target_datetime": "2026-05-17T18:00:00+09:00",
      "feature_datetime": "2026-05-17T17:00:00+09:00",
      "strategy": "pattern",
      "top_forecast_dong": "논현1동",
      "top_forecast_score": 1,
      "status": "waiting_for_observed_snapshot"
    },
    {
      "generated_at": "2026-05-17T18:42:34+09:00",
      "target_datetime": "2026-05-17T19:00:00+09:00",
      "feature_datetime": "2026-05-17T18:00:00+09:00",
      "strategy": "pattern",
      "top_forecast_dong": "논현1동",
      "top_forecast_score": 1,
      "status": "waiting_for_observed_snapshot"
    },
    {
      "generated_at": "2026-05-17T19:38:16+09:00",
      "target_datetime": "2026-05-17T20:00:00+09:00",
      "feature_datetime": "2026-05-17T19:00:00+09:00",
      "strategy": "pattern",
      "top_forecast_dong": "논현1동",
      "top_forecast_score": 1,
      "status": "waiting_for_observed_snapshot"
    },
    {
      "generated_at": "2026-05-17T20:33:33+09:00",
      "target_datetime": "2026-05-17T21:00:00+09:00",
      "feature_datetime": "2026-05-17T20:00:00+09:00",
      "strategy": "pattern",
      "top_forecast_dong": "역삼1동",
      "top_forecast_score": 1,
      "status": "waiting_for_observed_snapshot"
    },
    {
      "generated_at": "2026-05-17T21:34:31+09:00",
      "target_datetime": "2026-05-17T22:00:00+09:00",
      "feature_datetime": "2026-05-17T21:00:00+09:00",
      "strategy": "pattern",
      "top_forecast_dong": "논현1동",
      "top_forecast_score": 1,
      "status": "waiting_for_observed_snapshot"
    },
    {
      "generated_at": "2026-05-17T22:39:46+09:00",
      "target_datetime": "2026-05-17T23:00:00+09:00",
      "feature_datetime": "2026-05-17T22:00:00+09:00",
      "strategy": "pattern",
      "top_forecast_dong": "논현1동",
      "top_forecast_score": 1,
      "status": "waiting_for_observed_snapshot"
    },
    {
      "generated_at": "2026-05-18T01:29:50+09:00",
      "target_datetime": "2026-05-18T02:00:00+09:00",
      "feature_datetime": "2026-05-18T01:00:00+09:00",
      "strategy": "pattern",
      "top_forecast_dong": "역삼1동",
      "top_forecast_score": 1,
      "status": "waiting_for_target_time"
    }
  ]
}
