{
  "generated_at": "2026-05-08T18:43:43.328Z",
  "generated_at_kst": "2026. 05. 09. 03:43",
  "automation_window": {
    "until_kst": "2026-05-06 09:00",
    "purpose": "overnight model QA and public-data proxy model improvement"
  },
  "latest_api_collection": {
    "citydata_collected_at": "2026-05-08T18:43:33.617Z",
    "raw_citydata_path": "data/raw/citydata/2026-05-09/0343.json",
    "raw_weather_path": "data/raw/weather/2026-05-09/0343.json",
    "kma_ok": true,
    "kma_status": 200,
    "weather_meaning": "강수 없음. 데이터 누락이 아닙니다.",
    "kma_nowcast": {
      "temperature_c": 10.2,
      "precipitation_mm_1h": 0,
      "precipitation_type_code": "0",
      "humidity_pct": 65,
      "wind_speed_ms": 0.6
    }
  },
  "latest_targets": {
    "demand_target_datetime": "2026-05-09T04:00:00+09:00",
    "traffic_target_datetime": "2026-05-09T04:00:00+09:00",
    "taxi_pressure_target_datetime": "2026-05-09T04:00:00+09:00"
  },
  "top_predictions": {
    "taxi_pressure": [
      {
        "rank": 1,
        "dong_name": "삼성1동",
        "score": 0.5212,
        "action_level": "watch"
      },
      {
        "rank": 2,
        "dong_name": "논현1동",
        "score": 0.3781,
        "action_level": "low"
      },
      {
        "rank": 3,
        "dong_name": "청담동",
        "score": 0.2021,
        "action_level": "low"
      },
      {
        "rank": 4,
        "dong_name": "역삼1동",
        "score": 0.1664,
        "action_level": "low"
      },
      {
        "rank": 5,
        "dong_name": "신사동",
        "score": 0.1192,
        "action_level": "low"
      }
    ],
    "demand_proxy": [
      {
        "rank": 1,
        "dong_name": "삼성1동",
        "score": 1,
        "action_level": "-"
      },
      {
        "rank": 2,
        "dong_name": "역삼1동",
        "score": 0.293,
        "action_level": "-"
      },
      {
        "rank": 3,
        "dong_name": "논현1동",
        "score": 0.2144,
        "action_level": "-"
      }
    ],
    "traffic_congestion": [
      {
        "rank": 1,
        "dong_name": "논현1동",
        "score": 0.8336,
        "action_level": "-"
      },
      {
        "rank": 2,
        "dong_name": "청담동",
        "score": 0.4466,
        "action_level": "-"
      },
      {
        "rank": 3,
        "dong_name": "신사동",
        "score": 0.3548,
        "action_level": "-"
      }
    ],
    "demand_guardrail": [
      {
        "rank": 1,
        "dong_name": "삼성1동",
        "priority": 0.4505,
        "pressure": 0.5664,
        "confidence": 0.5451,
        "level": "medium",
        "risks": "pattern_fallback_used, weak_2026_proxy_validation"
      },
      {
        "rank": 2,
        "dong_name": "논현1동",
        "priority": 0.3513,
        "pressure": 0.4011,
        "confidence": 0.724,
        "level": "high",
        "risks": "pattern_fallback_used, recent_rank_volatility"
      },
      {
        "rank": 3,
        "dong_name": "역삼1동",
        "priority": 0.2205,
        "pressure": 0.2732,
        "confidence": 0.5715,
        "level": "medium",
        "risks": "pattern_fallback_used, signals_disagree"
      },
      {
        "rank": 4,
        "dong_name": "청담동",
        "priority": 0.2142,
        "pressure": 0.238,
        "confidence": 0.7777,
        "level": "high",
        "risks": "pattern_fallback_used"
      },
      {
        "rank": 5,
        "dong_name": "삼성2동",
        "priority": 0.1702,
        "pressure": 0.1927,
        "confidence": 0.741,
        "level": "high",
        "risks": "pattern_fallback_used"
      }
    ]
  },
  "population_pressure": {
    "target_datetime": "2026-05-09 04:00",
    "live_poi_count": 7,
    "covered_dong_count": 6,
    "forecast_population_mid_sum": 66250,
    "top_dongs": [
      {
        "rank": 1,
        "dong_name": "삼성2동",
        "forecast_population_mid_sum": 17000,
        "avg_poi_pressure_score": 0.318
      },
      {
        "rank": 2,
        "dong_name": "역삼1동",
        "forecast_population_mid_sum": 30750,
        "avg_poi_pressure_score": 0.305
      },
      {
        "rank": 3,
        "dong_name": "논현1동",
        "forecast_population_mid_sum": 6750,
        "avg_poi_pressure_score": 0.218
      },
      {
        "rank": 4,
        "dong_name": "신사동",
        "forecast_population_mid_sum": 8250,
        "avg_poi_pressure_score": 0.204
      },
      {
        "rank": 5,
        "dong_name": "청담동",
        "forecast_population_mid_sum": 1750,
        "avg_poi_pressure_score": 0.136
      }
    ]
  },
  "guardrail": {
    "target_datetime": "2026-05-09T04:00:00+09:00",
    "forecast_strategy": "pattern",
    "baseline_strength_score": 0.6303,
    "model_vs_pattern_mae_improvement_pct": 6.5,
    "top_monitoring_dong": {
      "rank": 1,
      "dong_name": "삼성1동",
      "priority": 0.4505,
      "pressure": 0.5664,
      "confidence": 0.5451,
      "level": "medium",
      "risks": "pattern_fallback_used, weak_2026_proxy_validation"
    }
  },
  "validation": {
    "taxi_pressure_status": "has_completed_comparison",
    "taxi_pressure_log_count": 44,
    "taxi_pressure_completed_count": 1,
    "taxi_pressure_waiting_count": 43,
    "latest_pressure_comparison": {
      "kind": "completed",
      "generated_at": "2026-05-08T17:40:06.290Z",
      "target_datetime": "2026-05-09T03:00:00+09:00",
      "feature_datetime": "2026-05-09T02:00:00+09:00",
      "actual_observed_at": "2026-05-08T18:43:33.617Z",
      "actual_snapshot_path": "data/raw/traffic/2026-05-09/0343.json",
      "comparison_type": "taxi_pressure_policy_check_vs_observed_road_signal",
      "note": "Policy check only — not accuracy scoring. Taxi pressure combines demand proxy + traffic volume + congestion + road accessibility. Observed road congestion alone is not a valid ground-truth label for a composite policy score. Spearman here is a supplementary signal; a negative value does not mean the model is wrong.",
      "overall": {
        "check_type": "policy_check",
        "row_count": 9,
        "congestion_mae": 0.1953,
        "speed_mae_kmh": 1.83,
        "priority_vs_road_congestion_spearman": 0.3833,
        "pressure_vs_congestion_rank_spearman": 0.3333,
        "speed_rank_spearman": 0.8833,
        "top_predicted_priority_dong": "논현1동",
        "top_actual_congestion_dong": "논현1동",
        "same_top_dong": true
      },
      "rows": [
        {
          "dong_name": "논현1동",
          "predicted_dispatch_priority_score": 0.8657,
          "predicted_taxi_pressure_score": 0.9195,
          "predicted_movement_demand_score": 1,
          "predicted_traffic_volume_score": 1,
          "predicted_congestion_score": 0.8461,
          "actual_congestion_score": 0.562,
          "congestion_error": 0.2841,
          "abs_congestion_error": 0.2841,
          "predicted_avg_speed_kmh": 20,
          "actual_avg_speed_kmh": 21.3,
          "speed_error_kmh": -1.3,
          "abs_speed_error_kmh": 1.3,
          "actual_link_count": 19,
          "predicted_priority_rank": 1,
          "predicted_pressure_rank": 1,
          "actual_congestion_rank": 1,
          "predicted_slowest_rank": 1,
          "actual_slowest_rank": 2
        },
        {
          "dong_name": "역삼1동",
          "predicted_dispatch_priority_score": 0.3616,
          "predicted_taxi_pressure_score": 0.4805,
          "predicted_movement_demand_score": 0.7611,
          "predicted_traffic_volume_score": 0.0571,
          "predicted_congestion_score": 0.2387,
          "actual_congestion_score": 0.511,
          "congestion_error": -0.2723,
          "abs_congestion_error": 0.2723,
          "predicted_avg_speed_kmh": 24.1,
          "actual_avg_speed_kmh": 23.1,
          "speed_error_kmh": 1,
          "abs_speed_error_kmh": 1,
          "actual_link_count": 91,
          "predicted_priority_rank": 2,
          "predicted_pressure_rank": 3,
          "actual_congestion_rank": 4,
          "predicted_slowest_rank": 4,
          "actual_slowest_rank": 3
        },
        {
          "dong_name": "삼성1동",
          "predicted_dispatch_priority_score": 0.3564,
          "predicted_taxi_pressure_score": 0.4816,
          "predicted_movement_demand_score": 0.7448,
          "predicted_traffic_volume_score": 0.1289,
          "predicted_congestion_score": 0.2593,
          "actual_congestion_score": 0.474,
          "congestion_error": -0.2147,
          "abs_congestion_error": 0.2147,
          "predicted_avg_speed_kmh": 27.5,
          "actual_avg_speed_kmh": 27,
          "speed_error_kmh": 0.5,
          "abs_speed_error_kmh": 0.5,
          "actual_link_count": 12,
          "predicted_priority_rank": 3,
          "predicted_pressure_rank": 2,
          "actual_congestion_rank": 7,
          "predicted_slowest_rank": 7,
          "actual_slowest_rank": 7
        },
        {
          "dong_name": "청담동",
          "predicted_dispatch_priority_score": 0.3153,
          "predicted_taxi_pressure_score": 0.4261,
          "predicted_movement_demand_score": 0.4222,
          "predicted_traffic_volume_score": 0.4319,
          "predicted_congestion_score": 0.4711,
          "actual_congestion_score": 0.488,
          "congestion_error": -0.0169,
          "abs_congestion_error": 0.0169,
          "predicted_avg_speed_kmh": 23.1,
          "actual_avg_speed_kmh": 25.7,
          "speed_error_kmh": -2.6,
          "abs_speed_error_kmh": 2.6,
          "actual_link_count": 33,
          "predicted_priority_rank": 4,
          "predicted_pressure_rank": 4,
          "actual_congestion_rank": 6,
          "predicted_slowest_rank": 3,
          "actual_slowest_rank": 6
        },
        {
          "dong_name": "대치4동",
          "predicted_dispatch_priority_score": 0.2878,
          "predicted_taxi_pressure_score": 0.389,
          "predicted_movement_demand_score": 0.5586,
          "predicted_traffic_volume_score": 0.0614,
          "predicted_congestion_score": 0.2767,
          "actual_congestion_score": 0.554,
          "congestion_error": -0.2773,
          "abs_congestion_error": 0.2773,
          "predicted_avg_speed_kmh": 21.9,
          "actual_avg_speed_kmh": 20.8,
          "speed_error_kmh": 1.1,
          "abs_speed_error_kmh": 1.1,
          "actual_link_count": 18,
          "predicted_priority_rank": 5,
          "predicted_pressure_rank": 5,
          "actual_congestion_rank": 2,
          "predicted_slowest_rank": 2,
          "actual_slowest_rank": 1
        },
        {
          "dong_name": "논현2동",
          "predicted_dispatch_priority_score": 0.1981,
          "predicted_taxi_pressure_score": 0.2677,
          "predicted_movement_demand_score": 0.3905,
          "predicted_traffic_volume_score": 0.1578,
          "predicted_congestion_score": 0.1738,
          "actual_congestion_score": 0.2,
          "congestion_error": -0.0262,
          "abs_congestion_error": 0.0262,
          "predicted_avg_speed_kmh": 36.1,
          "actual_avg_speed_kmh": 39.4,
          "speed_error_kmh": -3.3,
          "abs_speed_error_kmh": 3.3,
          "actual_link_count": 2,
          "predicted_priority_rank": 6,
          "predicted_pressure_rank": 6,
          "actual_congestion_rank": 9,
          "predicted_slowest_rank": 8,
          "actual_slowest_rank": 8
        },
        {
          "dong_name": "삼성2동",
          "predicted_dispatch_priority_score": 0.1471,
          "predicted_taxi_pressure_score": 0.1989,
          "predicted_movement_demand_score": 0.2396,
          "predicted_traffic_volume_score": 0.0502,
          "predicted_congestion_score": 0.223,
          "actual_congestion_score": 0.539,
          "congestion_error": -0.316,
          "abs_congestion_error": 0.316,
          "predicted_avg_speed_kmh": 26.5,
          "actual_avg_speed_kmh": 23.6,
          "speed_error_kmh": 2.9,
          "abs_speed_error_kmh": 2.9,
          "actual_link_count": 23,
          "predicted_priority_rank": 7,
          "predicted_pressure_rank": 7,
          "actual_congestion_rank": 3,
          "predicted_slowest_rank": 5,
          "actual_slowest_rank": 4
        },
        {
          "dong_name": "신사동",
          "predicted_dispatch_priority_score": 0.1322,
          "predicted_taxi_pressure_score": 0.1787,
          "predicted_movement_demand_score": 0.0765,
          "predicted_traffic_volume_score": 0.3494,
          "predicted_congestion_score": 0.3625,
          "actual_congestion_score": 0.343,
          "congestion_error": 0.0195,
          "abs_congestion_error": 0.0195,
          "predicted_avg_speed_kmh": 41.7,
          "actual_avg_speed_kmh": 41,
          "speed_error_kmh": 0.7,
          "abs_speed_error_kmh": 0.7,
          "actual_link_count": 47,
          "predicted_priority_rank": 8,
          "predicted_pressure_rank": 8,
          "actual_congestion_rank": 8,
          "predicted_slowest_rank": 9,
          "actual_slowest_rank": 9
        },
        {
          "dong_name": "역삼2동",
          "predicted_dispatch_priority_score": 0.0373,
          "predicted_taxi_pressure_score": 0.0505,
          "predicted_movement_demand_score": 0,
          "predicted_traffic_volume_score": 0,
          "predicted_congestion_score": 0.1615,
          "actual_congestion_score": 0.492,
          "congestion_error": -0.3305,
          "abs_congestion_error": 0.3305,
          "predicted_avg_speed_kmh": 27.3,
          "actual_avg_speed_kmh": 24.2,
          "speed_error_kmh": 3.1,
          "abs_speed_error_kmh": 3.1,
          "actual_link_count": 19,
          "predicted_priority_rank": 9,
          "predicted_pressure_rank": 9,
          "actual_congestion_rank": 5,
          "predicted_slowest_rank": 6,
          "actual_slowest_rank": 5
        }
      ]
    },
    "poi_forecast_comparison_type": "citydata_poi_1h_forecast_vs_observed_citydata",
    "poi_forecast_completed_count": 0,
    "poi_forecast_waiting_count": 1,
    "latest_poi_forecast_comparison": {
      "kind": "waiting",
      "source_observed_at": "2026-05-08T18:15:00.000Z",
      "source_snapshot_path": "data/raw/citydata/2026-05-09/0343.json",
      "target_datetime": "2026-05-08T19:00:00.000Z",
      "forecast_row_count": 7,
      "matched_row_count": 0,
      "status": "waiting_for_future_citydata_observation"
    },
    "live_log_count": 76
  },
  "dispatch_effect": {
    "method": "proxy_counterfactual_v1",
    "interpretation": "Estimated pressure relief from monitoring units and incentive multipliers. This is a policy-planning proxy, not measured dispatch impact.",
    "intervention_area_count": 1,
    "total_monitoring_units": 2,
    "max_incentive_multiplier": 1.1,
    "total_positive_imbalance_before": 0.4,
    "estimated_total_positive_imbalance_after": 0.205,
    "estimated_total_relief_score": 0.195,
    "highest_relief_dong": "삼성1동"
  },
  "note": "This status tracks public-data proxy forecasts, not direct call-volume predictions."
}
