{
  "source": "gangnam_poi_feature_snapshot_v1",
  "generated_at": "2026-05-12T11:50:31.156Z",
  "raw_citydata_path": "data/raw/citydata/2026-05-12/2045.json",
  "official_reference": {
    "name": "Seoul real-time citydata OA-21285 update notice",
    "url": "https://data.seoul.go.kr/together/notice/datasetNoticeView.do?bbsCd=10008&ditcCd=&pageIndex=1&seq=27399e1302ead42db866fa14824c4c56"
  },
  "citydata_collection_count": 7,
  "live_poi_count": 0,
  "supplemental_poi_count": 6,
  "row_count": 6,
  "direct_citydata_rows": [],
  "supplemental_watchlist": [
    {
      "source_status": "osm_context_only",
      "poi_code": "osm-hakdong-station",
      "poi_name": "학동역",
      "area_name": "학동역",
      "coverage_dong": "논현2동",
      "category": "station_context",
      "lon": 127.03075,
      "lat": 37.513957,
      "observed_at": null,
      "current_population_min": null,
      "current_population_max": null,
      "current_population_mid": null,
      "current_congestion_level": null,
      "current_congestion_score": null,
      "current_traffic_index": null,
      "current_traffic_score": null,
      "current_traffic_speed_kmh": null,
      "current_weather_temp_c": null,
      "current_precipitation_type": null,
      "demand_proxy_score": null,
      "poi_pressure_score": null,
      "population_forecast_1h": null,
      "forecast_population_delta": null,
      "forecast_population_delta_pct": null,
      "note": "No confirmed Seoul citydata hotspot code; keep as map/context POI."
    },
    {
      "source_status": "osm_context_only",
      "poi_code": "osm-eonju-station",
      "poi_name": "언주역",
      "area_name": "언주역",
      "coverage_dong": "역삼1동",
      "category": "station_context",
      "lon": 127.033875,
      "lat": 37.507321,
      "observed_at": null,
      "current_population_min": null,
      "current_population_max": null,
      "current_population_mid": null,
      "current_congestion_level": null,
      "current_congestion_score": null,
      "current_traffic_index": null,
      "current_traffic_score": null,
      "current_traffic_speed_kmh": null,
      "current_weather_temp_c": null,
      "current_precipitation_type": null,
      "demand_proxy_score": null,
      "poi_pressure_score": null,
      "population_forecast_1h": null,
      "forecast_population_delta": null,
      "forecast_population_delta_pct": null,
      "note": "No confirmed Seoul citydata hotspot code; keep as map/context POI."
    },
    {
      "source_status": "osm_context_only",
      "poi_code": "osm-gangnam-gu-office-station",
      "poi_name": "강남구청역",
      "area_name": "강남구청역",
      "coverage_dong": "청담동",
      "category": "station_context",
      "lon": 127.041286,
      "lat": 37.517176,
      "observed_at": null,
      "current_population_min": null,
      "current_population_max": null,
      "current_population_mid": null,
      "current_congestion_level": null,
      "current_congestion_score": null,
      "current_traffic_index": null,
      "current_traffic_score": null,
      "current_traffic_speed_kmh": null,
      "current_weather_temp_c": null,
      "current_precipitation_type": null,
      "demand_proxy_score": null,
      "poi_pressure_score": null,
      "population_forecast_1h": null,
      "forecast_population_delta": null,
      "forecast_population_delta_pct": null,
      "note": "No confirmed Seoul citydata hotspot code; keep as map/context POI."
    },
    {
      "source_status": "osm_context_only",
      "poi_code": "osm-daechi-station",
      "poi_name": "대치역",
      "area_name": "대치역",
      "coverage_dong": "대치4동",
      "category": "station_context",
      "lon": 127.063,
      "lat": 37.4945,
      "observed_at": null,
      "current_population_min": null,
      "current_population_max": null,
      "current_population_mid": null,
      "current_congestion_level": null,
      "current_congestion_score": null,
      "current_traffic_index": null,
      "current_traffic_score": null,
      "current_traffic_speed_kmh": null,
      "current_weather_temp_c": null,
      "current_precipitation_type": null,
      "demand_proxy_score": null,
      "poi_pressure_score": null,
      "population_forecast_1h": null,
      "forecast_population_delta": null,
      "forecast_population_delta_pct": null,
      "note": "No confirmed Seoul citydata hotspot code; keep as map/context POI."
    },
    {
      "source_status": "osm_context_only",
      "poi_code": "osm-hanti-station",
      "poi_name": "한티역",
      "area_name": "한티역",
      "coverage_dong": "대치4동",
      "category": "station_context",
      "lon": 127.0522,
      "lat": 37.4977,
      "observed_at": null,
      "current_population_min": null,
      "current_population_max": null,
      "current_population_mid": null,
      "current_congestion_level": null,
      "current_congestion_score": null,
      "current_traffic_index": null,
      "current_traffic_score": null,
      "current_traffic_speed_kmh": null,
      "current_weather_temp_c": null,
      "current_precipitation_type": null,
      "demand_proxy_score": null,
      "poi_pressure_score": null,
      "population_forecast_1h": null,
      "forecast_population_delta": null,
      "forecast_population_delta_pct": null,
      "note": "No confirmed Seoul citydata hotspot code; keep as map/context POI."
    },
    {
      "source_status": "osm_context_only",
      "poi_code": "osm-teheran-ro",
      "poi_name": "테헤란로",
      "area_name": "테헤란로",
      "coverage_dong": "역삼1동",
      "category": "road_corridor_context",
      "lon": 127.0395,
      "lat": 37.503,
      "observed_at": null,
      "current_population_min": null,
      "current_population_max": null,
      "current_population_mid": null,
      "current_congestion_level": null,
      "current_congestion_score": null,
      "current_traffic_index": null,
      "current_traffic_score": null,
      "current_traffic_speed_kmh": null,
      "current_weather_temp_c": null,
      "current_precipitation_type": null,
      "demand_proxy_score": null,
      "poi_pressure_score": null,
      "population_forecast_1h": null,
      "forecast_population_delta": null,
      "forecast_population_delta_pct": null,
      "note": "Corridor-level context POI. Use TOPIS/road graph rather than citydata hotspot population."
    }
  ],
  "top_live_poi": null,
  "note": "Citydata rows have current population/congestion/road speed. Supplemental watchlist rows are OSM/context POIs and must not be treated as live citydata observations."
}
