{
  "source": "taxi_pressure_fusion_model_v1",
  "model_type": "public_data_proxy_ensemble",
  "generated_at": "2026-05-16T22:24:20.670Z",
  "target_datetime": "2026-05-17T08:00:00+09:00",
  "feature_datetime": "2026-05-17T07:00:00+09:00",
  "horizon_hours": 1,
  "inputs": {
    "movement_demand_forecast": "public/forecast/latest.json",
    "traffic_forecast": "public/traffic-forecast/latest.json",
    "current_traffic_snapshot": "data/processed/traffic/citydata_dong_traffic_latest.json"
  },
  "formula": {
    "taxi_pressure_score": "0.52 * movement_demand_score + 0.20 * traffic_volume_score + 0.28 * congestion_pressure",
    "congestion_pressure": "1 - road_accessibility_score",
    "road_accessibility_score": "0.68 * (1 - predicted_congestion_score) + 0.32 * clamp(predicted_avg_speed_kmh / 35)",
    "dispatch_priority_score": "0.74 * taxi_pressure_score + 0.26 * max(0, movement_demand_score - road_accessibility_score)"
  },
  "interpretation": "Ranks dong-level future taxi-dispatch pressure from public proxy signals. It is not direct taxi-call volume.",
  "regions": [
    {
      "dong_name": "논현1동",
      "taxi_pressure_score": 0.7447,
      "dispatch_priority_score": 0.6463,
      "demand_access_gap": 0.3663,
      "predicted_movement_demand_score": 0.6758,
      "predicted_movement_raw": 48.376136,
      "predicted_traffic_volume_score": 1,
      "predicted_traffic_volume_proxy": 14434.322,
      "predicted_congestion_score": 0.8191,
      "predicted_avg_speed_kmh": 20.4,
      "road_accessibility_score": 0.3095,
      "current_congestion_score": 0.524,
      "current_avg_speed_kmh": 23,
      "current_link_count": 19,
      "confidence": 0.6539,
      "action_level": "medium",
      "action": "light_relocation_or_queue_watch",
      "monitoring_units": 2,
      "incentive_multiplier": 1.15
    },
    {
      "dong_name": "삼성1동",
      "taxi_pressure_score": 0.6988,
      "dispatch_priority_score": 0.6214,
      "demand_access_gap": 0.4008,
      "predicted_movement_demand_score": 1,
      "predicted_movement_raw": 67.705039,
      "predicted_traffic_volume_score": 0.3331,
      "predicted_traffic_volume_proxy": 5618.137,
      "predicted_congestion_score": 0.4254,
      "predicted_avg_speed_kmh": 22.8,
      "road_accessibility_score": 0.5992,
      "current_congestion_score": 0.576,
      "current_avg_speed_kmh": 21.6,
      "current_link_count": 12,
      "confidence": 0.581,
      "action_level": "medium",
      "action": "light_relocation_or_queue_watch",
      "monitoring_units": 2,
      "incentive_multiplier": 1.15
    },
    {
      "dong_name": "역삼1동",
      "taxi_pressure_score": 0.3747,
      "dispatch_priority_score": 0.2773,
      "demand_access_gap": 0,
      "predicted_movement_demand_score": 0.5651,
      "predicted_movement_raw": 41.773971,
      "predicted_traffic_volume_score": 0.0497,
      "predicted_traffic_volume_proxy": 1872.6,
      "predicted_congestion_score": 0.2353,
      "predicted_avg_speed_kmh": 24.8,
      "road_accessibility_score": 0.7467,
      "current_congestion_score": 0.538,
      "current_avg_speed_kmh": 22.2,
      "current_link_count": 91,
      "confidence": 0.706,
      "action_level": "low",
      "action": "hold",
      "monitoring_units": 0,
      "incentive_multiplier": 1
    },
    {
      "dong_name": "논현2동",
      "taxi_pressure_score": 0.3631,
      "dispatch_priority_score": 0.2687,
      "demand_access_gap": 0,
      "predicted_movement_demand_score": 0.5861,
      "predicted_movement_raw": 43.028353,
      "predicted_traffic_volume_score": 0.0785,
      "predicted_traffic_volume_proxy": 2253.353,
      "predicted_congestion_score": 0.1756,
      "predicted_avg_speed_kmh": 31.4,
      "road_accessibility_score": 0.8477,
      "current_congestion_score": 0.334,
      "current_avg_speed_kmh": 29.6,
      "current_link_count": 2,
      "confidence": 0.4768,
      "action_level": "low",
      "action": "hold",
      "monitoring_units": 0,
      "incentive_multiplier": 1
    },
    {
      "dong_name": "대치4동",
      "taxi_pressure_score": 0.346,
      "dispatch_priority_score": 0.256,
      "demand_access_gap": 0,
      "predicted_movement_demand_score": 0.5142,
      "predicted_movement_raw": 38.739103,
      "predicted_traffic_volume_score": 0.0167,
      "predicted_traffic_volume_proxy": 1436.189,
      "predicted_congestion_score": 0.2273,
      "predicted_avg_speed_kmh": 22.5,
      "road_accessibility_score": 0.7312,
      "current_congestion_score": 0.571,
      "current_avg_speed_kmh": 19.9,
      "current_link_count": 18,
      "confidence": 0.6435,
      "action_level": "low",
      "action": "hold",
      "monitoring_units": 0,
      "incentive_multiplier": 1
    },
    {
      "dong_name": "청담동",
      "taxi_pressure_score": 0.3302,
      "dispatch_priority_score": 0.2444,
      "demand_access_gap": 0,
      "predicted_movement_demand_score": 0.1239,
      "predicted_movement_raw": 15.47003,
      "predicted_traffic_volume_score": 0.6383,
      "predicted_traffic_volume_proxy": 9653.519,
      "predicted_congestion_score": 0.5831,
      "predicted_avg_speed_kmh": 24.4,
      "road_accessibility_score": 0.5066,
      "current_congestion_score": 0.493,
      "current_avg_speed_kmh": 25.3,
      "current_link_count": 33,
      "confidence": 0.706,
      "action_level": "low",
      "action": "hold",
      "monitoring_units": 0,
      "incentive_multiplier": 1
    },
    {
      "dong_name": "신사동",
      "taxi_pressure_score": 0.161,
      "dispatch_priority_score": 0.1192,
      "demand_access_gap": 0,
      "predicted_movement_demand_score": 0.0308,
      "predicted_movement_raw": 9.918889,
      "predicted_traffic_volume_score": 0.374,
      "predicted_traffic_volume_proxy": 6158.796,
      "predicted_congestion_score": 0.3687,
      "predicted_avg_speed_kmh": 41.6,
      "road_accessibility_score": 0.7493,
      "current_congestion_score": 0.36,
      "current_avg_speed_kmh": 41.7,
      "current_link_count": 47,
      "confidence": 0.706,
      "action_level": "low",
      "action": "hold",
      "monitoring_units": 0,
      "incentive_multiplier": 1
    },
    {
      "dong_name": "삼성2동",
      "taxi_pressure_score": 0.0859,
      "dispatch_priority_score": 0.0636,
      "demand_access_gap": 0,
      "predicted_movement_demand_score": 0.0879,
      "predicted_movement_raw": 13.321922,
      "predicted_traffic_volume_score": 0,
      "predicted_traffic_volume_proxy": 1215.261,
      "predicted_congestion_score": 0.1319,
      "predicted_avg_speed_kmh": 29.1,
      "road_accessibility_score": 0.8564,
      "current_congestion_score": 0.347,
      "current_avg_speed_kmh": 26.9,
      "current_link_count": 23,
      "confidence": 0.6956,
      "action_level": "low",
      "action": "hold",
      "monitoring_units": 0,
      "incentive_multiplier": 1
    },
    {
      "dong_name": "역삼2동",
      "taxi_pressure_score": 0.0661,
      "dispatch_priority_score": 0.0489,
      "demand_access_gap": 0,
      "predicted_movement_demand_score": 0,
      "predicted_movement_raw": 8.082734,
      "predicted_traffic_volume_score": 0.0277,
      "predicted_traffic_volume_proxy": 1581.397,
      "predicted_congestion_score": 0.2076,
      "predicted_avg_speed_kmh": 26.8,
      "road_accessibility_score": 0.7839,
      "current_congestion_score": 0.501,
      "current_avg_speed_kmh": 24.1,
      "current_link_count": 19,
      "confidence": 0.6539,
      "action_level": "low",
      "action": "hold",
      "monitoring_units": 0,
      "incentive_multiplier": 1
    }
  ]
}
